oxcc_utils/__init__.py
oxcc_utils-10.0.0.dist-info/METADATA
oxcc_utils-10.0.0.dist-info/WHEEL
oxcc_utils-10.0.0.dist-info/top_level.txt
oxcc_utils-10.0.0.dist-info/RECORD
