Metadata-Version: 2.4
Name: oxcc_utils
Version: 10.0.0
Summary: Dependency confusion demo for learning purposes
Author: KF 0xCC
Author-email: kf118@pm.me
Dynamic: author
Dynamic: author-email
Dynamic: summary
